check_execution_order.py
check_execution_order-0.1.1.dist-info/LICENSE
check_execution_order-0.1.1.dist-info/METADATA
check_execution_order-0.1.1.dist-info/WHEEL
check_execution_order-0.1.1.dist-info/entry_points.txt
check_execution_order-0.1.1.dist-info/top_level.txt
check_execution_order-0.1.1.dist-info/RECORD
